sqlxfluff/__init__.py
sqlxfluff/constants.py
sqlxfluff/formatters/__init__.py
sqlxfluff/formatters/base.py
sqlxfluff/formatters/indent.py
sqlxfluff/formatters/javascript.py
sqlxfluff/formatters/sqlx.py
sqlxfluff/linting.py
sqlxfluff/main.py
sqlxfluff/parsing.py
sqlxfluff-0.3.1.dist-info/LICENSE.md
sqlxfluff-0.3.1.dist-info/METADATA
sqlxfluff-0.3.1.dist-info/WHEEL
sqlxfluff-0.3.1.dist-info/entry_points.txt
sqlxfluff-0.3.1.dist-info/RECORD
