Metadata-Version: 2.1
Name: sqlxfluff
Version: 0.3.1
Summary: 
Author: Coby Simmons
Author-email: cobysimmons01@gmail.com
Requires-Python: >=3.11,<4.0
Classifier: Programming Language :: Python :: 3
Classifier: Programming Language :: Python :: 3.11
Classifier: Programming Language :: Python :: 3.12
Requires-Dist: sqlfluff (>=3.2.0,<4.0.0)
Requires-Dist: termcolor (>=2.3.0,<3.0.0)
